mcp_server_snowflake/__init__.py
mcp_server_snowflake/__main__.py
mcp_server_snowflake/server.py
mcp_server_snowflake-0.3.8.dist-info/METADATA
mcp_server_snowflake-0.3.8.dist-info/WHEEL
mcp_server_snowflake-0.3.8.dist-info/entry_points.txt
mcp_server_snowflake-0.3.8.dist-info/licenses/LICENSE
mcp_server_snowflake-0.3.8.dist-info/RECORD
